Metadata-Version: 1.0
Name: zabbix-ecs-connector
Version: 0.0.3
Summary: Implementation of Zabbix AWS ECS connector
Home-page: https://github.com/akomic/zabbix-ecs-connector
Author: Alen Komic
Author-email: akomic@gmail.com
License: UNKNOWN
Keywords: monitoring,zabbix,AWS,ECS
Platform: UNKNOWN
